.gitignore
CHANGES.txt
CONTRIBUTORS.txt
MANIFEST.in
README.rst
bootstrap.py
buildout.cfg
setup.py
docs/LICENSE.GPL
docs/LICENSE.txt
src/collective/__init__.py
src/collective.select2.egg-info/PKG-INFO
src/collective.select2.egg-info/SOURCES.txt
src/collective.select2.egg-info/dependency_links.txt
src/collective.select2.egg-info/entry_points.txt
src/collective.select2.egg-info/namespace_packages.txt
src/collective.select2.egg-info/not-zip-safe
src/collective.select2.egg-info/requires.txt
src/collective.select2.egg-info/top_level.txt
src/collective/select2/__init__.py
src/collective/select2/browser.py
src/collective/select2/browser.zcml
src/collective/select2/configure.zcml
src/collective/select2/converter.py
src/collective/select2/demo.py
src/collective/select2/display.pt
src/collective/select2/field.py
src/collective/select2/hidden.pt
src/collective/select2/input.pt
src/collective/select2/interfaces.py
src/collective/select2/widget.py
src/collective/select2/widgets.zcml
src/collective/select2/profiles/default/browserlayer.xml
src/collective/select2/profiles/default/cssregistry.xml
src/collective/select2/profiles/default/jsregistry.xml
src/collective/select2/profiles/default/metadata.xml
src/collective/select2/static/select2widgets.js
src/collective/select2/static/select2/select2-spinner.gif
src/collective/select2/static/select2/select2.css
src/collective/select2/static/select2/select2.min.js
src/collective/select2/static/select2/select2.png
src/collective/select2/static/select2/select2x2.png