Metadata-Version: 1.1
Name: collective.select2
Version: 1.0b
Summary: User token widget
Home-page: http://svn.plone.org/svn/collective/
Author: UNKNOWN
Author-email: UNKNOWN
License: gpl
Platform: UNKNOWN
Classifier: Programming Language :: Python
